rgd/__init__.py
rgd/apps.py
rgd/datastore.py
rgd/filters.py
rgd/permissions.py
rgd/serializers.py
rgd/signals.py
rgd/urls.py
rgd/utility.py
rgd/views.py
rgd/admin/__init__.py
rgd/admin/collection.py
rgd/admin/common.py
rgd/admin/file.py
rgd/admin/fileset.py
rgd/admin/mixins.py
rgd/configuration/__init__.py
rgd/configuration/configuration.py
rgd/management/commands/_data_helper.py
rgd/management/commands/rgd_s3_files.py
rgd/management/commands/whitelist_email.py
rgd/migrations/0001_initial.py
rgd/migrations/0002_alter_spatialasset_files.py
rgd/migrations/0003_checksumfile_created_by.py
rgd/migrations/0004_alter_checksumfile_status.py
rgd/migrations/0005_auto_20211105_1715.py
rgd/migrations/0006_auto_20211210_1744.py
rgd/migrations/0007_auto_20211215_0608.py
rgd/migrations/0008_collection_description.py
rgd/migrations/0009_alter_checksumfile_collection_and_more.py
rgd/migrations/__init__.py
rgd/models/__init__.py
rgd/models/collection.py
rgd/models/common.py
rgd/models/constants.py
rgd/models/file.py
rgd/models/fileset.py
rgd/models/mixins.py
rgd/models/transform.py
rgd/models/utils.py
rgd/rest/__init__.py
rgd/rest/authentication.py
rgd/rest/base.py
rgd/rest/mixins.py
rgd/rest/viewsets.py
rgd/static/rgd/favicon.png
rgd/static/rgd/css/.gitignore
rgd/static/rgd/css/style.css
rgd/static/rgd/css/sass/_base.scss
rgd/static/rgd/css/sass/_transitions.scss
rgd/static/rgd/css/sass/_variables.scss
rgd/static/rgd/css/sass/style.scss
rgd/tasks/__init__.py
rgd/tasks/helpers.py
rgd/tasks/jobs.py
rgd/templates/rgd/spatialentry_list.html
rgd/templates/rgd/statistics.html
rgd/templates/rgd/_base/base.html
rgd/templates/rgd/_base/detail.html
rgd/templates/rgd/_base/list_view.html
rgd/templates/rgd/_base/search_view.html
rgd/templates/rgd/_base/spatial_detail.html
rgd/templates/rgd/_include/empty_viewer.html
rgd/templates/rgd/_include/geojson_reader.html
rgd/templates/rgd/_include/navbar.html
rgd/templates/rgd/_include/not_logged_in.html
rgd/templates/rgd/_include/search_fields.html
django_rgd-0.3.11.dist-info/METADATA
django_rgd-0.3.11.dist-info/WHEEL
django_rgd-0.3.11.dist-info/dependency_links.txt
django_rgd-0.3.11.dist-info/top_level.txt
django_rgd-0.3.11.dist-info/RECORD
