Metadata-Version: 2.1
Name: django-rgd
Version: 0.3.11
Summary: UNKNOWN
Home-page: https://github.com/ResonantGeoData/ResonantGeoData
Author: Kitware, Inc.
Author-email: rgd@kitware.com
License: Apache 2.0
Platform: UNKNOWN
Classifier: Development Status :: 3 - Alpha
Classifier: Environment :: Web Environment
Classifier: Framework :: Django :: 3.0
Classifier: Framework :: Django
Classifier: Intended Audience :: Developers
Classifier: License :: OSI Approved :: Apache Software License
Classifier: Operating System :: OS Independent
Classifier: Programming Language :: Python :: 3
Classifier: Programming Language :: Python :: 3.8
Classifier: Programming Language :: Python
Requires-Python: >=3.8
Requires-Dist: boto3
Requires-Dist: celery
Requires-Dist: django (>=3.2)
Requires-Dist: django-allauth
Requires-Dist: django-click
Requires-Dist: django-crum
Requires-Dist: django-extensions
Requires-Dist: django-filter
Requires-Dist: django-girder-utils
Requires-Dist: django-model-utils
Requires-Dist: django-oauth-toolkit
Requires-Dist: django-s3-file-field[minio]
Requires-Dist: djangorestframework
Requires-Dist: drf-yasg
Requires-Dist: filelock
Requires-Dist: flower
Requires-Dist: GDAL
Requires-Dist: pooch
Requires-Dist: psutil
Requires-Dist: psycopg2
Requires-Dist: python-magic
Requires-Dist: typing-extensions
Provides-Extra: configuration
Requires-Dist: django-composed-configuration[dev] ; extra == 'configuration'
Requires-Dist: django-configurations[database,email] (>=0.19.2) ; extra == 'configuration'
Requires-Dist: django-cache-url ; extra == 'configuration'
Requires-Dist: redis ; extra == 'configuration'
Provides-Extra: fuse
Requires-Dist: numpy ; extra == 'fuse'
Requires-Dist: simple-httpfs ; extra == 'fuse'
